setup.py
py_http_errors/__init__.py
py_http_errors/_base.py
py_http_errors/_ext_flask.py
py_http_errors.egg-info/PKG-INFO
py_http_errors.egg-info/SOURCES.txt
py_http_errors.egg-info/dependency_links.txt
py_http_errors.egg-info/not-zip-safe
py_http_errors.egg-info/top_level.txt