Metadata-Version: 2.1
Name: py-http-errors
Version: 2023.3.27
Summary: Python Common HTTP Exceptions for API-JSON-Response
Home-page: https://github.com/dodoru/py-http-errors
Author: Nico Ning
Author-email: dodoru@foxmail.com
License: MIT
Platform: any
Classifier: License :: OSI Approved :: MIT License
Classifier: Operating System :: OS Independent
Classifier: Programming Language :: Python
Classifier: Programming Language :: Python :: 3.6
Classifier: Programming Language :: Python :: 3.7
Classifier: Programming Language :: Python :: 3.8
Classifier: Programming Language :: Python :: 3.9
Classifier: Topic :: Utilities
Classifier: Development Status :: 4 - Beta
